LICENSE
MANIFEST.in
README.md
setup.py
pyalot/__init__.py
pyalot/__main__.py
pyalot/pyalot.py
pyalot.egg-info/PKG-INFO
pyalot.egg-info/SOURCES.txt
pyalot.egg-info/dependency_links.txt
pyalot.egg-info/entry_points.txt
pyalot.egg-info/requires.txt
pyalot.egg-info/top_level.txt