Metadata-Version: 1.1
Name: pyalot
Version: 0.1
Summary: Send Pushalot notifications from the command line or from Python code
Home-page: http://github.com/mlesniew/pyalot
Author: Michał Leśniewski
Author-email: mlesniew@gmail.com
License: GPLv3
Keywords: pushalot push notification windowsphone
Platform: UNKNOWN
Classifier: Development Status :: 2 - Pre-Alpha
Classifier: Environment :: Console
Classifier: Intended Audience :: Developers
Classifier: Intended Audience :: End Users/Desktop
Classifier: Intended Audience :: System Administrators
Classifier: License :: OSI Approved :: GNU General Public License v3 (GPLv3)
Classifier: Programming Language :: Python :: 2.7
Classifier: Programming Language :: Python
Classifier: Topic :: Software Development :: Libraries :: Python Modules
